{
  "updated_at": "2025-09-25T10:25:38+00:00",
  "count": 100,
  "data": [
    {
      "id": "e8yqjw",
      "source": "https://x.com/PALOW_/status/1557304749078511617/photo/1",
      "added_at": "2025-09-25T08:31:45+00:00"
    },
    {
      "id": "zpmdej",
      "source": "",
      "added_at": "2025-09-25T08:31:45+00:00"
    },
    {
      "id": "vpxoyl",
      "source": "https://www.pixiv.net/en/artworks/129533559",
      "added_at": "2025-09-25T08:31:46+00:00"
    },
    {
      "id": "7jgjx9",
      "source": "https://www.bilibili.com/opus/1054207436585435174",
      "added_at": "2025-09-25T08:31:46+00:00"
    },
    {
      "id": "ogxyml",
      "source": "https://www.pixiv.net/artworks/129436746",
      "added_at": "2025-09-25T08:31:46+00:00"
    },
    {
      "id": "e8oolk",
      "source": "https://x.com/ddcc0123/status/1923377155766898994",
      "added_at": "2025-09-25T08:31:47+00:00"
    },
    {
      "id": "21emrx",
      "source": "https://twitter.com/PinaxPinakes/status/1946430078101205500",
      "added_at": "2025-09-25T08:31:47+00:00"
    },
    {
      "id": "ogxo7m",
      "source": "https://www.pixiv.net/en/artworks/35872930",
      "added_at": "2025-09-25T08:31:47+00:00"
    },
    {
      "id": "ly8q5p",
      "source": "https://www.bilibili.com/opus/1114197070205419527",
      "added_at": "2025-09-25T08:31:47+00:00"
    },
    {
      "id": "k83y1q",
      "source": "https://www.pixiv.net/artworks/106593162",
      "added_at": "2025-09-25T08:31:48+00:00"
    },
    {
      "id": "x6x2zo",
      "source": "https://x.com/alllisso_/status/1906067272608751936",
      "added_at": "2025-09-25T08:31:48+00:00"
    },
    {
      "id": "3qkllv",
      "source": "https://www.pixiv.net/en/artworks/124447052",
      "added_at": "2025-09-25T08:31:48+00:00"
    },
    {
      "id": "rrvz5j",
      "source": "",
      "added_at": "2025-09-25T08:31:49+00:00"
    },
    {
      "id": "je39yw",
      "source": "https://www.pixiv.net/artworks/133090234",
      "added_at": "2025-09-25T08:31:49+00:00"
    },
    {
      "id": "yq8lgk",
      "source": "https://www.pixiv.net/en/artworks/134425467",
      "added_at": "2025-09-25T08:31:49+00:00"
    },
    {
      "id": "je56ry",
      "source": "https://www.pixiv.net/en/artworks/132690593",
      "added_at": "2025-09-25T08:31:49+00:00"
    },
    {
      "id": "6lo587",
      "source": "https://www.pixiv.net/artworks/129961812",
      "added_at": "2025-09-25T08:31:50+00:00"
    },
    {
      "id": "d85qqm",
      "source": "https://www.pixiv.net/en/artworks/106823791",
      "added_at": "2025-09-25T08:31:50+00:00"
    },
    {
      "id": "jx6lqm",
      "source": "https://www.pixiv.net/en/artworks/55325876",
      "added_at": "2025-09-25T08:31:51+00:00"
    },
    {
      "id": "ly3pxl",
      "source": "https://www.pixiv.net/users/20778107",
      "added_at": "2025-09-25T08:31:51+00:00"
    },
    {
      "id": "21g3qg",
      "source": "",
      "added_at": "2025-09-25T08:31:52+00:00"
    },
    {
      "id": "k83k77",
      "source": "",
      "added_at": "2025-09-25T08:31:52+00:00"
    },
    {
      "id": "rq3mw7",
      "source": "https://x.com/ShunyaYamashita/status/1589213600920776706?t=RRpY59TqLwJy-jL3-wV7UQ&s=19",
      "added_at": "2025-09-25T09:25:59+00:00"
    },
    {
      "id": "3q9rly",
      "source": "https://www.pixiv.net/en/artworks/131605118",
      "added_at": "2025-09-25T09:26:02+00:00"
    },
    {
      "id": "9omemd",
      "source": "https://www.pixiv.net/en/artworks/132084476",
      "added_at": "2025-09-25T09:26:02+00:00"
    },
    {
      "id": "rrv9qm",
      "source": "https://www.pixiv.net/artworks/109834735",
      "added_at": "2025-09-25T09:26:04+00:00"
    },
    {
      "id": "21kjey",
      "source": "https://www.pixiv.net/en/artworks/123010238",
      "added_at": "2025-09-25T09:26:04+00:00"
    },
    {
      "id": "xe19lv",
      "source": "https://www.pixiv.net/en/artworks/131052059",
      "added_at": "2025-09-25T09:26:04+00:00"
    },
    {
      "id": "qr6dlq",
      "source": "https://www.pixiv.net/en/artworks/103784301",
      "added_at": "2025-09-25T09:26:06+00:00"
    },
    {
      "id": "exd5z8",
      "source": "https://www.pixiv.net/en/artworks/99459363",
      "added_at": "2025-09-25T09:26:09+00:00"
    },
    {
      "id": "yxzplk",
      "source": "https://www.pixiv.net/en/artworks/128780403",
      "added_at": "2025-09-25T09:26:09+00:00"
    },
    {
      "id": "yq8w67",
      "source": "https://www.pixiv.net/en/artworks/134308930",
      "added_at": "2025-09-25T09:26:11+00:00"
    },
    {
      "id": "po81rj",
      "source": "https://www.pixiv.net/en/artworks/10530513",
      "added_at": "2025-09-25T09:26:13+00:00"
    },
    {
      "id": "1q3lzw",
      "source": "https://x.com/tabakko/status/1930214714447147199",
      "added_at": "2025-09-25T09:26:14+00:00"
    },
    {
      "id": "qr6wqd",
      "source": "https://www.pixiv.net/en/artworks/133137133",
      "added_at": "2025-09-25T09:26:14+00:00"
    },
    {
      "id": "gw8oge",
      "source": "https://www.pixiv.net/en/artworks/133051167",
      "added_at": "2025-09-25T09:26:16+00:00"
    },
    {
      "id": "yxzl3l",
      "source": "",
      "added_at": "2025-09-25T09:26:18+00:00"
    },
    {
      "id": "m38e1m",
      "source": "https://www.pixiv.net/en/artworks/128805855",
      "added_at": "2025-09-25T09:26:19+00:00"
    },
    {
      "id": "6lkqml",
      "source": "https://www.pixiv.net/artworks/131417983",
      "added_at": "2025-09-25T09:26:19+00:00"
    },
    {
      "id": "1q8wl1",
      "source": "https://aercinae.carrd.co/",
      "added_at": "2025-09-25T09:26:20+00:00"
    },
    {
      "id": "mldlw1",
      "source": "https://www.pixiv.net/artworks/94290378",
      "added_at": "2025-09-25T09:26:20+00:00"
    },
    {
      "id": "gw7zmd",
      "source": "https://x.com/haedgie/status/1949654678817353876",
      "added_at": "2025-09-25T09:26:21+00:00"
    },
    {
      "id": "5ydyj7",
      "source": "https://www.fanbox.cc/@houk1se1/posts/9918344",
      "added_at": "2025-09-25T09:26:23+00:00"
    },
    {
      "id": "21kkm9",
      "source": "https://www.miyoushe.com/zzz/article/61293854",
      "added_at": "2025-09-25T09:26:24+00:00"
    },
    {
      "id": "xelrwv",
      "source": "",
      "added_at": "2025-09-25T09:26:24+00:00"
    },
    {
      "id": "lymxmy",
      "source": "https://x.com/1shtarr/status/1946030094046347412",
      "added_at": "2025-09-25T09:26:24+00:00"
    },
    {
      "id": "d85ljo",
      "source": "https://www.pixiv.net/artworks/110206195",
      "added_at": "2025-09-25T09:26:26+00:00"
    },
    {
      "id": "21gpog",
      "source": "https://twitter.com/kjudraw/status/1922889040656756918",
      "added_at": "2025-09-25T09:26:52+00:00"
    },
    {
      "id": "zpmokw",
      "source": "",
      "added_at": "2025-09-25T09:26:55+00:00"
    },
    {
      "id": "gw8p53",
      "source": "https://www.pixiv.net/artworks/119248935",
      "added_at": "2025-09-25T09:27:48+00:00"
    },
    {
      "id": "ly3q7r",
      "source": "https://www.pixiv.net/en/artworks/133167830",
      "added_at": "2025-09-25T09:27:51+00:00"
    },
    {
      "id": "d8prwg",
      "source": "https://www.pixiv.net/artworks/133534446",
      "added_at": "2025-09-25T09:27:56+00:00"
    },
    {
      "id": "yq77og",
      "source": "https://www.pixiv.net/artworks/119791514",
      "added_at": "2025-09-25T09:27:56+00:00"
    },
    {
      "id": "pokyvj",
      "source": "",
      "added_at": "2025-09-25T09:27:58+00:00"
    },
    {
      "id": "vpmo7p",
      "source": "https://www.pixiv.net/en/artworks/128107479",
      "added_at": "2025-09-25T09:28:08+00:00"
    },
    {
      "id": "lyqm5r",
      "source": "https://www.pixiv.net/en/artworks/128877199",
      "added_at": "2025-09-25T09:28:08+00:00"
    },
    {
      "id": "d8p73g",
      "source": "",
      "added_at": "2025-09-25T09:28:20+00:00"
    },
    {
      "id": "yqmlmx",
      "source": "https://www.reddit.com/r/evangelion/comments/w5er5t/unit_00_%E7%B6%BE%E6%B3%A2_%E3%83%AC%E3%82%A4_rei_digital_poster_me/",
      "added_at": "2025-09-25T10:25:28+00:00"
    },
    {
      "id": "ogdzd5",
      "source": "https://www.reddit.com/r/evangelion/comments/w5er5t/unit_00_%E7%B6%BE%E6%B3%A2_%E3%83%AC%E3%82%A4_rei_digital_poster_me/",
      "added_at": "2025-09-25T10:25:29+00:00"
    },
    {
      "id": "qr9jml",
      "source": "https://www.pixiv.net/en/artworks/127440533",
      "added_at": "2025-09-25T10:25:29+00:00"
    },
    {
      "id": "852q62",
      "source": "https://www.pixiv.net/en/artworks/124860699",
      "added_at": "2025-09-25T10:25:29+00:00"
    },
    {
      "id": "mlpprm",
      "source": "https://x.com/washiya0/status/1924480246033887686",
      "added_at": "2025-09-25T10:25:29+00:00"
    },
    {
      "id": "3q9w3v",
      "source": "https://www.pixiv.net/artworks/125713670",
      "added_at": "2025-09-25T10:25:29+00:00"
    },
    {
      "id": "d8p83m",
      "source": "https://weibo.com/6033575010/PCjTA15tU?pagetype=profilefeed",
      "added_at": "2025-09-25T10:25:29+00:00"
    },
    {
      "id": "9o5jq8",
      "source": "https://twitter.com/rucarachi/status/1936421564410700183",
      "added_at": "2025-09-25T10:25:29+00:00"
    },
    {
      "id": "rq3v8j",
      "source": "https://www.pixiv.net/en/artworks/129181593",
      "added_at": "2025-09-25T10:25:29+00:00"
    },
    {
      "id": "gw7myq",
      "source": "",
      "added_at": "2025-09-25T10:25:29+00:00"
    },
    {
      "id": "qr98yl",
      "source": "https://www.pixiv.net/users/18912354",
      "added_at": "2025-09-25T10:25:30+00:00"
    },
    {
      "id": "3qkkdy",
      "source": "https://www.pixiv.net/en/artworks/127633159",
      "added_at": "2025-09-25T10:25:30+00:00"
    },
    {
      "id": "mldy7y",
      "source": "https://www.pixiv.net/en/artworks/132439582",
      "added_at": "2025-09-25T10:25:32+00:00"
    },
    {
      "id": "6lqz1q",
      "source": "https://www.pixiv.net/en/artworks/110126559",
      "added_at": "2025-09-25T10:25:32+00:00"
    },
    {
      "id": "gwj8p3",
      "source": "https://www.pixiv.net/en/artworks/129339284",
      "added_at": "2025-09-25T10:25:32+00:00"
    },
    {
      "id": "pok6lp",
      "source": "https://www.pixiv.net/artworks/133629111",
      "added_at": "2025-09-25T10:25:32+00:00"
    },
    {
      "id": "21eg8m",
      "source": "https://www.pixiv.net/en/artworks/103147610",
      "added_at": "2025-09-25T10:25:32+00:00"
    },
    {
      "id": "ly9zjl",
      "source": "https://www.pixiv.net/en/users/60715675",
      "added_at": "2025-09-25T10:25:32+00:00"
    },
    {
      "id": "3q9egy",
      "source": "https://x.com/ericx_gasi/status/1909768669879845373",
      "added_at": "2025-09-25T10:25:34+00:00"
    },
    {
      "id": "po2qwm",
      "source": "https://www.pixiv.net/en/artworks/131401513",
      "added_at": "2025-09-25T10:25:34+00:00"
    },
    {
      "id": "je52zm",
      "source": "https://www.pixiv.net/en/artworks/91049850",
      "added_at": "2025-09-25T10:25:35+00:00"
    },
    {
      "id": "mlqmo8",
      "source": "",
      "added_at": "2025-09-25T10:25:35+00:00"
    },
    {
      "id": "rrv6xw",
      "source": "",
      "added_at": "2025-09-25T10:25:35+00:00"
    },
    {
      "id": "e8zzy8",
      "source": "https://www.pixiv.net/en/artworks/78387732",
      "added_at": "2025-09-25T10:25:35+00:00"
    },
    {
      "id": "je3ygw",
      "source": "https://www.pixiv.net/en/artworks/109741727",
      "added_at": "2025-09-25T10:25:35+00:00"
    },
    {
      "id": "k83qpd",
      "source": "https://www.pixiv.net/artworks/130295579",
      "added_at": "2025-09-25T10:25:35+00:00"
    },
    {
      "id": "e87mqo",
      "source": "https://gf.bilibili.com/item/detail/1108300036?noTitleBar=1&from=mall-up_itemDetail&msource=auto-dynamic",
      "added_at": "2025-09-25T10:25:35+00:00"
    },
    {
      "id": "d85weo",
      "source": "https://www.pixiv.net/artworks/121031925",
      "added_at": "2025-09-25T10:25:35+00:00"
    },
    {
      "id": "1q3k63",
      "source": "https://www.weibo.com/5219954675/PyTMbeWE8",
      "added_at": "2025-09-25T10:25:36+00:00"
    },
    {
      "id": "po8pqj",
      "source": "https://x.com/yoneyamai/status/1761751794559172712/photo/1",
      "added_at": "2025-09-25T10:25:36+00:00"
    },
    {
      "id": "w58mv7",
      "source": "https://gruvbox-wallpapers.pages.dev/wallpapers/anime/anime_girl_plus_rockets.png",
      "added_at": "2025-09-25T10:25:36+00:00"
    },
    {
      "id": "x6xq2v",
      "source": "",
      "added_at": "2025-09-25T10:25:36+00:00"
    },
    {
      "id": "ogdrk5",
      "source": "https://www.pixiv.net/artworks/129657581",
      "added_at": "2025-09-25T10:25:37+00:00"
    },
    {
      "id": "9omgp1",
      "source": "",
      "added_at": "2025-09-25T10:25:37+00:00"
    },
    {
      "id": "ly38qp",
      "source": "https://x.com/null___u/status/1951886889570685359",
      "added_at": "2025-09-25T10:25:37+00:00"
    },
    {
      "id": "3lxvw9",
      "source": "https://www.pixiv.net/artworks/101922657",
      "added_at": "2025-09-25T10:25:37+00:00"
    },
    {
      "id": "5y7ro7",
      "source": "https://www.pixiv.net/en/artworks/133805999",
      "added_at": "2025-09-25T10:25:37+00:00"
    },
    {
      "id": "w5qo2x",
      "source": "https://www.artstation.com/artwork/d8N2Pe",
      "added_at": "2025-09-25T10:25:37+00:00"
    },
    {
      "id": "d8x3em",
      "source": "https://www.pixiv.net/users/16275159",
      "added_at": "2025-09-25T10:25:37+00:00"
    },
    {
      "id": "xe5m3v",
      "source": "https://www.pixiv.net/artworks/108923025",
      "added_at": "2025-09-25T10:25:38+00:00"
    },
    {
      "id": "yq7x3x",
      "source": "https://www.pixiv.net/en/artworks/129394151",
      "added_at": "2025-09-25T10:25:38+00:00"
    },
    {
      "id": "po83gp",
      "source": "https://x.com/KiriyumeBun/status/1937487280366846173",
      "added_at": "2025-09-25T10:25:38+00:00"
    },
    {
      "id": "d8gxj3",
      "source": "https://www.pixiv.net/en/artworks/130475841",
      "added_at": "2025-09-25T10:25:38+00:00"
    }
  ]
}
